Metadata-Version: 1.1
Name: pepper_kinematics
Version: 0.0.6
Summary: Pepper Inverse/Forward Kinematics library
Home-page: http://www.sugarsweetrobotics.com/
Author: ysuga
Author-email: ysuga@ysuga.net
License: GPLv3
Download-URL: https://github.com/sugarsweetrobotics/python_pepper_kinematics
Platform: UNKNOWN
Classifier: Development Status :: 5 - Production/Stable
Classifier: Environment :: Console
Classifier: Intended Audience :: Developers
Classifier: License :: OSI Approved :: GNU General Public License v3 (GPLv3)
Classifier: Natural Language :: English
Classifier: Operating System :: OS Independent
Classifier: Programming Language :: Python
Classifier: Topic :: Scientific/Engineering
